dokdo/__init__.py
dokdo/dokdo.py
dokdo-1.0.0.dist-info/LICENSE
dokdo-1.0.0.dist-info/METADATA
dokdo-1.0.0.dist-info/WHEEL
dokdo-1.0.0.dist-info/entry_points.txt
dokdo-1.0.0.dist-info/top_level.txt
dokdo-1.0.0.dist-info/RECORD
