Metadata-Version: 2.1
Name: dokdo
Version: 1.0.0
Summary: The beautiful island of the Republic of Korea, Dokdo.
Home-page: https://becky2sawyer.github.io/dokdo
Author: pysatellite
Author-email: pysatellite@gmail.com
License: GNU General Public License (GPL)
Project-URL: Bug Tracker, https://github.com/becky2sawyer/dokdo/issues
Platform: macOS
Classifier: Programming Language :: Python :: 3
Classifier: License :: OSI Approved :: GNU General Public License (GPL)
Classifier: Operating System :: OS Independent
Requires-Python: >=3.6
License-File: LICENSE
